astronomy/__init__.py
astronomy/astronomy.py
astronomy_engine-2.1.18.dist-info/LICENSE
astronomy_engine-2.1.18.dist-info/METADATA
astronomy_engine-2.1.18.dist-info/WHEEL
astronomy_engine-2.1.18.dist-info/top_level.txt
astronomy_engine-2.1.18.dist-info/RECORD
