Metadata-Version: 2.1
Name: astronomy-engine
Version: 2.1.18
Summary: Astronomy calculation for Sun, Moon, and planets.
Home-page: https://github.com/cosinekitty/astronomy
Author: Donald Cross
Author-email: cosinekitty@gmail.com
License: MIT License
Classifier: Intended Audience :: Science/Research
Classifier: License :: OSI Approved :: MIT License
Classifier: Programming Language :: Python :: 3.7
License-File: LICENSE
